{
  "project_info": {
    "project_number": "230219820111",
    "firebase_url": "https://on-demand--player.firebaseio.com",
    "project_id": "on-demand-youtube-player",
    "storage_bucket": "on-demand-youtube-player.appspot.com"
  },
  "client": [
    {
      "client_info": {
        "mobilesdk_app_id": "1:230219820111:android:0e31807a76d7404a",
        "android_client_info": {
          "package_name": "com.vcoders.on_demand_youtube_player"
        }
      },
      "oauth_client": [
        {
          "client_id": "230219820111-j7td2ffbc9hrk1ec61qj88kqp2d2v030.apps.googleusercontent.com",
          "client_type": 3
        },
        {
          "client_id": "230219820111-69tifv19m2h5hrpma9urc66lc6d7uq6p.apps.googleusercontent.com",
          "client_type": 3
        },
        {
          "client_id": "230219820111-dmechksjcf0bfusru5gru02klel3i55d.apps.googleusercontent.com",
          "client_type": 3
        },
        {
          "client_id": "230219820111-4sppgoniu3psv0hjdh0jc50hkf38jdca.apps.googleusercontent.com",
          "client_type": 1,
          "android_info": {
            "package_name": "com.vcoders.on_demand_youtube_player",
            "certificate_hash": "f13cc417d685fab992e467fd683351a23cbceb4b"
          }
        },
        {
          "client_id": "230219820111-dmechksjcf0bfusru5gru02klel3i55d.apps.googleusercontent.com",
          "client_type": 3
        }
      ],
      "api_key": [
        {
          "current_key": "AIzaSyAcV6X_KqBVUkyahRVAd2Zo-0ex7RLuzsg"
        }
      ],
      "services": {
        "analytics_service": {
          "status": 1
        },
        "appinvite_service": {
          "status": 2,
          "other_platform_oauth_client": [
            {
              "client_id": "230219820111-j7td2ffbc9hrk1ec61qj88kqp2d2v030.apps.googleusercontent.com",
              "client_type": 3
            }
          ]
        },
        "ads_service": {
          "status": 2
        }
      }
    }
  ],
  "configuration_version": "1"
}